python_markdown_comments/__init__.py
python_markdown_comments-1.1.0.dist-info/LICENSE.md
python_markdown_comments-1.1.0.dist-info/WHEEL
python_markdown_comments-1.1.0.dist-info/METADATA
python_markdown_comments-1.1.0.dist-info/RECORD
