Metadata-Version: 2.1
Name: python-markdown-comments
Version: 1.1.0
Summary: A Python-Markdown extension to ignore html comments opened by three dashes.
Home-page: https://github.com/johanvergeer/python-markdown-comments
License: MIT
Keywords: markdown,extensions,comments
Author: Johan Vergeer
Author-email: johanvergeer@gmail.com
Requires-Python: >=3.6,<4.0
Classifier: Development Status :: 5 - Production/Stable
Classifier: Environment :: Console
Classifier: Intended Audience :: End Users/Desktop
Classifier: License :: OSI Approved :: MIT License
Classifier: Operating System :: OS Independent
Classifier: Programming Language :: Python
Classifier: Programming Language :: Python :: 3
Classifier: Programming Language :: Python :: 3.6
Classifier: Programming Language :: Python :: 3.7
Classifier: Programming Language :: Python :: 3.8
Classifier: Topic :: Internet :: WWW/HTTP
Classifier: Topic :: Software Development :: Libraries :: Python Modules
Requires-Dist: markdown (>=3.1.1,<4.0.0)
Project-URL: Repository, https://github.com/johanvergeer/python-markdown-comments
Project-URL: Source, https://github.com/johanvergeer/python-markdown-comments
Project-URL: Tracker, https://github.com/johanvergeer/python-markdown-comments/issues
